quinnstruct/__init__.py
quinnstruct/graph.py
quinnstruct/hashtable.py
quinnstruct/linklist.py
quinnstruct/queue.py
quinnstruct/stack.py
quinnstruct/tree.py
QuinnStruct-0.3.dist-info/LICENSE
QuinnStruct-0.3.dist-info/METADATA
QuinnStruct-0.3.dist-info/WHEEL
QuinnStruct-0.3.dist-info/top_level.txt
QuinnStruct-0.3.dist-info/RECORD
